<아이템 id="ITKC_MO" name="한국문집총간" org="한국고전번역원">
<레벨1 id="ITKC_MO_0001A" type="서지" 자료생성일="2003-09-04">
<레벨2 id="ITKC_MO_0001A_0160" type="권차" 자료생성일="2003-09-04">
			<메타정보>
				<제목정보>
					<제목><페이지 number="ITKC_MO_0001A_A001_087A"/><고유명사 type="서명">桂苑筆耕集</고유명사>卷之十五</제목>
				</제목정보>
			</메타정보>
		
<레벨3 id="ITKC_MO_0001A_0160_010" type="문체" 자료생성일="2003-09-04">
				<메타정보>
					<제목정보>
						<제목>齋詞 <원주>一十五首</원주></제목>
					</제목정보>
				</메타정보>
			
<레벨4 DCI="ITKC_MO_0001A_0160_010_0010_2003_A001_XML" id="ITKC_MO_0001A_0160_010_0010" type="최종정보" 자료생성일="2003-09-04">
					<메타정보>
						<제목정보>
							<제목>應天節齋詞</제목>
						</제목정보>
						<저자정보 type="필자">
							<저자>
								<한글성명>최치원</한글성명>
								<한자성명>崔致遠</한자성명>
							</저자>
						</저자정보>
						<간행정보>
							<집수번호>a001</집수번호>
						</간행정보>
						<분류정보>
							<분류항목 type="문체분류">
								<분류내용 type="대분류">哀祭類</분류내용>
								<분류내용 type="중분류">其他類</분류내용>
							</분류항목>
						</분류정보>
					</메타정보>
					<본문정보>
						<내용>
<단락 align="left" indent="0">道士某乙言。伏以聖人降生。王者嘉應。包天地之大<line/>
德。啓日月之殊祥。是以。電繞虹流。克符龍質。握乾披<line/>
<페이지 number="ITKC_MO_0001A_A001_087B"/>震。允叶龜書。伏惟聖神聰睿仁哲明孝皇帝。紫府眞<line/>
宗。丹陵寶命。孝理而勤修一德。化成而胥悅萬方。偶<line/>
以犬吠<고유명사 type="이름">堯</고유명사>威。熊驚漢御。猶軫泣辜之念。暫勞展義之<line/>
行。今者風振南薰。方在長嬴之節。星瞻北極。乃當誕<line/>
慶之辰。莫不山靈供萬歲之歡聲。<고유명사 type="이름">河伯</고유명사>獻千年之瑞<line/>
色。仰資聖壽。敢設仙齋。<고유명사 type="이름">廣成子</고유명사>之微言旣傳衆妙。華<line/>
封人之善祝實繫群誠。伏願德乃日新。禍當天悔。暫<line/>
興時雨。遍洗妖氛。高整鸞旗。早廻鳳輦。然後搜濟汾<line/>
之詠。撰封岱之儀。傳芳於玉葉金枝。積慶於天長地<line/>
久。使蠻戎率服。蠢植咸蘇。仰沐華胥之風。齊登仁壽<line/>
<페이지 number="ITKC_MO_0001A_A001_087C"/>之域。普天率土。永賀昇平。</단락>
						</내용>
					</본문정보>
					<연계정보>
						<연계항목 type="이미지" 연계시작="ITKC_MO_0001A_A001_087A" 연계종료="ITKC_MO_0001A_A001_087C"/>
						<연계항목 type="번역문" 연계시작="ITKC_BT_0001A_0160_010_0010" 연계종료="ITKC_BT_0001A_0160_010_0010"/>
					</연계정보>
				</레벨4>
<레벨4 DCI="ITKC_MO_0001A_0160_010_0020_2003_A001_XML" id="ITKC_MO_0001A_0160_010_0020" type="최종정보" 자료생성일="2003-09-04">
					<메타정보>
						<제목정보>
							<제목>應天節齋詞</제목>
						</제목정보>
						<저자정보 type="필자">
							<저자>
								<한글성명>최치원</한글성명>
								<한자성명>崔致遠</한자성명>
							</저자>
						</저자정보>
						<간행정보>
							<집수번호>a001</집수번호>
						</간행정보>
						<분류정보>
							<분류항목 type="문체분류">
								<분류내용 type="대분류">哀祭類</분류내용>
								<분류내용 type="중분류">其他類</분류내용>
							</분류항목>
						</분류정보>
					</메타정보>
					<본문정보>
						<내용>
<단락 align="left" indent="0">道士某乙言。伏以父天母地。帝道所以爲尊。貫月繞<line/>
星。靈符於是乎在。況覩一人有慶。固知萬壽無疆。伏<line/>
惟皇帝陛下。龍握丕圖。鳳資聖紀。播休聲於里社。標<line/>
盛禮於高禖。今者風調舜琴。日緩羲轡。曆草舒芳於<line/>
八葉。丹陵降瑞於千齡。謹設仙齋。仰陳善祝。伏願塵<line/>
銷九野。波息四溟。早廻西幸之儀。便擧東封之禮。一<line/>
千年之休運。高建武功。三十世之昌期。倍延福祚。允<line/>
諧大定。永賀中興。</단락>
						</내용>
					</본문정보>
					<연계정보>
						<연계항목 type="이미지" 연계시작="ITKC_MO_0001A_A001_087C" 연계종료="ITKC_MO_0001A_A001_087C"/>
						<연계항목 type="번역문" 연계시작="ITKC_BT_0001A_0160_010_0020" 연계종료="ITKC_BT_0001A_0160_010_0020"/>
					</연계정보>
				</레벨4>
<레벨4 DCI="ITKC_MO_0001A_0160_010_0030_2003_A001_XML" id="ITKC_MO_0001A_0160_010_0030" type="최종정보" 자료생성일="2003-09-04">
					<메타정보>
						<제목정보>
							<제목><페이지 number="ITKC_MO_0001A_A001_087D"/>應天節齋詞</제목>
						</제목정보>
						<저자정보 type="필자">
							<저자>
								<한글성명>최치원</한글성명>
								<한자성명>崔致遠</한자성명>
							</저자>
						</저자정보>
						<간행정보>
							<집수번호>a001</집수번호>
						</간행정보>
						<분류정보>
							<분류항목 type="문체분류">
								<분류내용 type="대분류">哀祭類</분류내용>
								<분류내용 type="중분류">其他類</분류내용>
							</분류항목>
						</분류정보>
					</메타정보>
					<본문정보>
						<내용>
<단락 align="left" indent="0">伏以瀨鄕白鹿。旣掛仙蹤。<고유명사 type="지명">函谷</고유명사>紫雲。果資王氣。積慶<line/>
於天長地久。傳葉於聖子神孫。耀玉京而我李長春。<line/>
演金籙而莊春永茂。伏惟皇帝陛下。三無稟德。萬有<line/>
覃恩。叶感星夢日之祥。掩四乳八眉之瑞。上天降聖。<line/>
爰乘解慍之風。列士修齊。況値晏陰之月。伏願峒山<line/>
順軌。<고유명사 type="지명">汾水</고유명사>廻鑾。迎萬歲之巖音。歸九重之天闕。享七<line/>
百年之休運。寰宇中興。守五千字之格言。兵戈大定。<line/>
仰祈玄鑑。永護皇居。</단락>
						</내용>
					</본문정보>
					<연계정보>
						<연계항목 type="이미지" 연계시작="ITKC_MO_0001A_A001_087D" 연계종료="ITKC_MO_0001A_A001_087D"/>
						<연계항목 type="번역문" 연계시작="ITKC_BT_0001A_0160_010_0030" 연계종료="ITKC_BT_0001A_0160_010_0030"/>
					</연계정보>
				</레벨4>
<레벨4 DCI="ITKC_MO_0001A_0160_010_0040_2003_A001_XML" id="ITKC_MO_0001A_0160_010_0040" type="최종정보" 자료생성일="2003-09-04">
					<메타정보>
						<제목정보>
							<제목>上元黃籙齋詞</제목>
						</제목정보>
						<저자정보 type="필자">
							<저자>
								<한글성명>최치원</한글성명>
								<한자성명>崔致遠</한자성명>
							</저자>
						</저자정보>
						<간행정보>
							<집수번호>a001</집수번호>
						</간행정보>
						<분류정보>
							<분류항목 type="문체분류">
								<분류내용 type="대분류">哀祭類</분류내용>
								<분류내용 type="중분류">其他類</분류내용>
							</분류항목>
						</분류정보>
					</메타정보>
					<본문정보>
						<내용>
<단락 align="left" indent="0"><페이지 number="ITKC_MO_0001A_A001_088A"/>年月朔。啓請如科儀。伏以有德不德。無名可名。自施<line/>
儵忽之功。莫究希微之旨。是以。紫府乃修心可到。玄<line/>
關非用力能開。臣志慕眞風。躬行正道。但以漢良前<line/>
筯。猶勞戰伐之謀。越蠡扁舟。未遂優閒之望。旣榮人<line/>
爵。須報主恩。誓殲無賴之徒。久練不祥之器。動拘俗<line/>
役。慮犯玄科。今則節已及於上元。災未銷於下界。謹<line/>
修常醮。仰貢微誠。所願梟覆頑巢。鳳廻仙駕。帝座與<line/>
三台永耀。王畿與九牧皆安。雷驚而蟄戶全開。風掃<line/>
而妖氛靜息。俾臣靈根日茂。至業天成。虎符提閫外<line/>
之權。終安澤國。虹節指壺中之境。得認家山。臣無任<line/>
<페이지 number="ITKC_MO_0001A_A001_088B"/>虔肅禱祠懇悃之至。謹辭。</단락>
						</내용>
					</본문정보>
					<연계정보>
						<연계항목 type="이미지" 연계시작="ITKC_MO_0001A_A001_087D" 연계종료="ITKC_MO_0001A_A001_088B"/>
						<연계항목 type="번역문" 연계시작="ITKC_BT_0001A_0160_010_0040" 연계종료="ITKC_BT_0001A_0160_010_0040"/>
					</연계정보>
				</레벨4>
<레벨4 DCI="ITKC_MO_0001A_0160_010_0050_2003_A001_XML" id="ITKC_MO_0001A_0160_010_0050" type="최종정보" 자료생성일="2003-09-04">
					<메타정보>
						<제목정보>
							<제목>中元齋詞</제목>
						</제목정보>
						<저자정보 type="필자">
							<저자>
								<한글성명>최치원</한글성명>
								<한자성명>崔致遠</한자성명>
							</저자>
						</저자정보>
						<간행정보>
							<집수번호>a001</집수번호>
						</간행정보>
						<분류정보>
							<분류항목 type="문체분류">
								<분류내용 type="대분류">哀祭類</분류내용>
								<분류내용 type="중분류">其他類</분류내용>
							</분류항목>
						</분류정보>
					</메타정보>
					<본문정보>
						<내용>
<단락 align="left" indent="0">年月朔。啓請如科儀。伏以道本強名。固絶琢磨之理。<line/>
身爲大患。深驚寵辱之機。能審自然而然。必知無可<line/>
不可。是以。雕詞贊美則乖妙音於混成。矯志求眞則<line/>
爽奇功於積學。冀標玉籍。在守金科。臣才謝半千。雖<line/>
慙賢路。心凝正一。早扣玄關。齋誠於八節三元。鍊志<line/>
於龍緘鳳蘊。但屬鯨翻逆浪。蜮噴毒沙。數年興蠹螫<line/>
之災。萬姓抱瘡痍之苦。三尺劍高提在手。須救危時。<line/>
六銖衣輕掛於身。未諧夙願。今謹因中元素節。大慶<line/>
<페이지 number="ITKC_MO_0001A_A001_088C"/>良辰。依寶壇而醮設常儀。企仙闕而拜申精懇。伏願<line/>
眞風蕩滌。玄澤滂流。吾君享萬歲於巖音。賢相耀六<line/>
符於渭訣。調<고유명사 type="이름">舜</고유명사>絃之美化。永復昌期。漏<고유명사 type="이름">湯</고유명사>網之兇徒。<line/>
咸歸顯戮。然後戴髮含齒。鱗潛羽翔。不知日用之功。<line/>
各遂天成之樂。俾臣代勳善繼。眞位高遷。留形於煙<line/>
閣雲臺。縱賞於芝田蕙圃。鑄金追想。終榮聖主之恩。<line/>
叱石閒遊。得效仙人之術。儻非過望。敢不精修。臣某<line/>
無任祈恩謝過虔禱懇悃之至。謹辭。</단락>
						</내용>
					</본문정보>
					<연계정보>
						<연계항목 type="이미지" 연계시작="ITKC_MO_0001A_A001_088B" 연계종료="ITKC_MO_0001A_A001_088C"/>
						<연계항목 type="번역문" 연계시작="ITKC_BT_0001A_0160_010_0050" 연계종료="ITKC_BT_0001A_0160_010_0050"/>
					</연계정보>
				</레벨4>
<레벨4 DCI="ITKC_MO_0001A_0160_010_0060_2003_A001_XML" id="ITKC_MO_0001A_0160_010_0060" type="최종정보" 자료생성일="2003-09-04">
					<메타정보>
						<제목정보>
							<제목>下元齋詞</제목>
						</제목정보>
						<저자정보 type="필자">
							<저자>
								<한글성명>최치원</한글성명>
								<한자성명>崔致遠</한자성명>
							</저자>
						</저자정보>
						<간행정보>
							<집수번호>a001</집수번호>
						</간행정보>
						<분류정보>
							<분류항목 type="문체분류">
								<분류내용 type="대분류">哀祭類</분류내용>
								<분류내용 type="중분류">其他類</분류내용>
							</분류항목>
						</분류정보>
					</메타정보>
					<본문정보>
						<내용>
<단락 align="left" indent="0">年月日。啓請如科儀。伏以敎資妙用。無爲而無不爲。<line/>
<페이지 number="ITKC_MO_0001A_A001_088D"/>道在勤行。不厭是以無厭。苟得捧持三寶。必能拯護<line/>
萬靈。須憑善建之根株。始覩混成之閫閾。故曰大丈<line/>
夫處其厚而不處其薄。居其實而不居其華者也。臣<line/>
雖塵役拘身。而雲裝挂志。大成是望。上達爲期。每依<line/>
<고유명사 type="이름">郭璞</고유명사>詩中。精調五石。願向<고유명사 type="이름">葛洪</고유명사>傳上。得寄一名。所以<line/>
仰欽象帝之先。豈在他人之後。聽爛柯翁之說則倍<line/>
惜光陰。覽<고유명사 type="서명">抱朴子</고유명사>之言則不虧忠信。但以卑棲俗累。<line/>
深握兵符。政刑之得失難調。賞罰之重輕易忒。暗惟<line/>
愆咎。莫補精修。況叨眞位之榮。恐負玄科之責。是以。<line/>
三元八節。顯醮遙祠。唯期致力於九層。未曾妨功於<line/>
<페이지 number="ITKC_MO_0001A_A001_089A"/>一簣。今則天吏扣應鍾之候。水官攬玄轡之時。月數<line/>
就盈。日辰在望。仰投靈地。敬設寶壇。備儀於琳几瓊<line/>
盤。注想於金臺銀闕。冀感通於良夕。能濟援於危時。<line/>
伏乞太上三尊。十方衆聖。曲垂玄鑑。俾遂丹誠。早廻<line/>
翠輦於<고유명사 type="지명">長安</고유명사>。復振皇風於正始。秉陶勻者永諧德化。<line/>
仗節鉞者共戢兵戎。波濤靜寢於四溟。氛霧豁開於<line/>
九野。樹下有推功之將。草間無求活之徒。至於翔翼<line/>
躍鱗。跂行喙息。偕登仁壽之域。不躡昏迷之途。使臣<line/>
深結道緣。遙申齋願。望三淸於通路。資一漑於良田。<line/>
此時枕越石之戈。暫妨高臥。他日把浮丘之袂。豈訝<line/>
<페이지 number="ITKC_MO_0001A_A001_089B"/>後來。臣某無任瀝懇投辭虔禱惶切之至。謹辭。</단락>
						</내용>
					</본문정보>
					<연계정보>
						<연계항목 type="이미지" 연계시작="ITKC_MO_0001A_A001_088C" 연계종료="ITKC_MO_0001A_A001_089B"/>
						<연계항목 type="번역문" 연계시작="ITKC_BT_0001A_0160_010_0060" 연계종료="ITKC_BT_0001A_0160_010_0060"/>
					</연계정보>
				</레벨4>
<레벨4 DCI="ITKC_MO_0001A_0160_010_0070_2003_A001_XML" id="ITKC_MO_0001A_0160_010_0070" type="최종정보" 자료생성일="2003-09-04">
					<메타정보>
						<제목정보>
							<제목>下元齋詞</제목>
						</제목정보>
						<저자정보 type="필자">
							<저자>
								<한글성명>최치원</한글성명>
								<한자성명>崔致遠</한자성명>
							</저자>
						</저자정보>
						<간행정보>
							<집수번호>a001</집수번호>
						</간행정보>
						<분류정보>
							<분류항목 type="문체분류">
								<분류내용 type="대분류">哀祭類</분류내용>
								<분류내용 type="중분류">其他類</분류내용>
							</분류항목>
						</분류정보>
					</메타정보>
					<본문정보>
						<내용>
<단락 align="left" indent="0">年月日。啓請如科儀。臣伏以測管窺天。雖乖曠望。揮<line/>
戈駐日。蓋感精誠。苟爲山之力不虧。則至海之期何<line/>
遠。仰玄門之善閉。遵妙道以勤行。但以爲子爲臣。曰<line/>
忠曰孝。旣增榮於國祿。願無忝於家勳。手握玉符。且<line/>
救寰中之難。志棲金籙。唯思象外之遊。每慮政失務<line/>
三。法虧畫一。雖愼撫綏於南兗。尙多愆咎於北酆。況<line/>
當翦寇爲期。弭兵未暇。今則月就盈數。日臨下元。遙<line/>
倣眞儀。敬陳齋法。儼星壇而稽首。想風馭以馳魂。伏<line/>
<페이지 number="ITKC_MO_0001A_A001_089C"/>乞太上三尊。十方衆聖。玄慈見蔭。良願克諧。翠華早<line/>
耀於秦雲。皇祚<고유명사 type="지명">永興</고유명사>於漢日。百官多慶。八裔同歡。寇<line/>
戎則銷燧象之災。幽滯則假燭龍之照。然後使臣世<line/>
官貞吉。道業滋成。遺榮待泛於五湖。企想潛通於三<line/>
島。作人間之都尉。蒯訓無心。拜天上之<고유명사 type="관직">侍郞</고유명사>。<고유명사 type="이름">沈羲</고유명사>有<line/>
望。唯願在家必達。終能直道而行。臣無任祈恩懺罪<line/>
虔切惶恐之至。謹辭。</단락>
						</내용>
					</본문정보>
					<연계정보>
						<연계항목 type="이미지" 연계시작="ITKC_MO_0001A_A001_089B" 연계종료="ITKC_MO_0001A_A001_089C"/>
						<연계항목 type="번역문" 연계시작="ITKC_BT_0001A_0160_010_0070" 연계종료="ITKC_BT_0001A_0160_010_0070"/>
					</연계정보>
				</레벨4>
<레벨4 DCI="ITKC_MO_0001A_0160_010_0080_2003_A001_XML" id="ITKC_MO_0001A_0160_010_0080" type="최종정보" 자료생성일="2003-09-04">
					<메타정보>
						<제목정보>
							<제목>上元齋詞</제목>
						</제목정보>
						<저자정보 type="필자">
							<저자>
								<한글성명>최치원</한글성명>
								<한자성명>崔致遠</한자성명>
							</저자>
						</저자정보>
						<간행정보>
							<집수번호>a001</집수번호>
						</간행정보>
						<분류정보>
							<분류항목 type="문체분류">
								<분류내용 type="대분류">哀祭類</분류내용>
								<분류내용 type="중분류">其他類</분류내용>
							</분류항목>
						</분류정보>
					</메타정보>
					<본문정보>
						<내용>
<단락 align="left" indent="0">年月日。啓請如科儀。臣仰察玄經。乃見道資衆甫。俯<line/>
稽聖典。則知神應至誠。是以。早詳病病之言。每勵賢<line/>
<페이지 number="ITKC_MO_0001A_A001_089D"/>賢之行。五音五色。實除耳目之娛。六甲六丁。潛致爪<line/>
牙之役。願躡輕飛之路。常敲衆妙之門。但屬戎馬生<line/>
郊。陳蛇奔穴。無苟免而臨難。不得已而用兵。蓋報主<line/>
恩。慮虧臣節。只誓顯誅寇孼。寧知暗積愆殃。雖軍律<line/>
克申。而眞科是懼。今以日延和景。月滿初元。遇吸新<line/>
吐故之辰。懺啄腐呑腥之罪。儼陳醮禮。敬薦齋誠。燈<line/>
耀九光。燼焚百和。寂寥塵外。幡幢靜設於星壇。髣髴<line/>
雲中。環佩似傳乎風馭。冀銷妖祲。仰告威靈。伏乞大<line/>
降玄慈。下從丹懇。萬乘永資於萬壽。百官皆荷於百<line/>
祥。戰場則荊棘叢生。農壤則麥禾茁茂。凡云蠢動。盡<line/>
<페이지 number="ITKC_MO_0001A_A001_090A"/>獲昭蘇。然後俾臣援溺功成。奉身以退。沖靈道遂。鼓<line/>
腹而遊。飽瓊蕊之糇糧。就瑤臺之蹊徑。遇圯上者終<line/>
諧素志。自有前蹤。入壺中者蓋感專心。寧無後望。旣<line/>
殊捕影。敢憚勞形。臣無任悔過祈恩虔切惶恐之至。<line/>
謹辭。</단락>
						</내용>
					</본문정보>
					<연계정보>
						<연계항목 type="이미지" 연계시작="ITKC_MO_0001A_A001_089C" 연계종료="ITKC_MO_0001A_A001_090A"/>
						<연계항목 type="번역문" 연계시작="ITKC_BT_0001A_0160_010_0080" 연계종료="ITKC_BT_0001A_0160_010_0080"/>
					</연계정보>
				</레벨4>
<레벨4 DCI="ITKC_MO_0001A_0160_010_0090_2003_A001_XML" id="ITKC_MO_0001A_0160_010_0090" type="최종정보" 자료생성일="2003-09-04">
					<메타정보>
						<제목정보>
							<제목>中元齋詞</제목>
						</제목정보>
						<저자정보 type="필자">
							<저자>
								<한글성명>최치원</한글성명>
								<한자성명>崔致遠</한자성명>
							</저자>
						</저자정보>
						<간행정보>
							<집수번호>a001</집수번호>
						</간행정보>
						<분류정보>
							<분류항목 type="문체분류">
								<분류내용 type="대분류">哀祭類</분류내용>
								<분류내용 type="중분류">其他類</분류내용>
							</분류항목>
						</분류정보>
					</메타정보>
					<본문정보>
						<내용>
<단락 align="left" indent="0">啓請如科儀。域中之四大難名。字之曰道。物外之三<line/>
淸在想。心以爲齋。豈圖滋福於一身。唯願洽恩於萬<line/>
彙。臣生逢聖日。志慕眞風。寧貪久視之門。有覬輕飛<line/>
之路。但以行先不殆。德貴有餘。每虔一氣以存思。非<line/>
<페이지 number="ITKC_MO_0001A_A001_090B"/>止三元而展敬。今則雲摧火影。風戛金聲。當中元積<line/>
慶之辰。謹修常醮。以下界罹災之事。仰告玄慈。一昨<line/>
夏景旣闌。秋成甚邇。而乃曠野則飛羊斂翅。深泉則<line/>
黑蜧藏鱗。嗷嗷之黔庶何依。烈烈之蒼穹莫訴。雖近<line/>
沾美澤。而尙慊農郊。伏乞太上三尊。十方衆聖。下從<line/>
精懇。大庇生靈。使風雨常調。煙塵永息。興聖祚於千<line/>
秋萬歲。振歡聲於四海九州。然後俾臣功名則與國<line/>
同休。道業則在家必達。水中泛泛。謝時態之澆浮。雲<line/>
外飄飄。逐仙蹤而騫翥。旣探珠而有望。寧種玉以無<line/>
因。臣不任祈恩救災懇禱虔惕之至。謹辭。</단락>
						</내용>
					</본문정보>
					<연계정보>
						<연계항목 type="이미지" 연계시작="ITKC_MO_0001A_A001_090A" 연계종료="ITKC_MO_0001A_A001_090B"/>
						<연계항목 type="번역문" 연계시작="ITKC_BT_0001A_0160_010_0090" 연계종료="ITKC_BT_0001A_0160_010_0090"/>
					</연계정보>
				</레벨4>
<레벨4 DCI="ITKC_MO_0001A_0160_010_0100_2003_A001_XML" id="ITKC_MO_0001A_0160_010_0100" type="최종정보" 자료생성일="2003-09-04">
					<메타정보>
						<제목정보>
							<제목><페이지 number="ITKC_MO_0001A_A001_090C"/>下元齋詞</제목>
						</제목정보>
						<저자정보 type="필자">
							<저자>
								<한글성명>최치원</한글성명>
								<한자성명>崔致遠</한자성명>
							</저자>
						</저자정보>
						<간행정보>
							<집수번호>a001</집수번호>
						</간행정보>
						<분류정보>
							<분류항목 type="문체분류">
								<분류내용 type="대분류">哀祭類</분류내용>
								<분류내용 type="중분류">其他類</분류내용>
							</분류항목>
						</분류정보>
					</메타정보>
					<본문정보>
						<내용>
<단락 align="left" indent="0">啓請如科儀。伏以混成至道。本在勤行。衆妙玄門。唯<line/>
資善閉。故曰修之身則其德乃貴。修之國則其德有<line/>
餘。旣能事少功多。可謂暫勞永逸。臣雖手提金鉞。而<line/>
心寄瑤臺。飄飄然自有良期。擾擾者誰知積學。是以。<line/>
三元致敬。一氣存思。佇天上之鷄聲。潛懸素望。待海<line/>
中之鶴信。每瀝丹誠。終冀用之則行。豈言深不可識。<line/>
今者謹齎薄禮。仰黷玄慈。所願轉茂靈根。漸抛俗界。<line/>
餌崦嵫之奇草。飮沆瀣之仙漿。漢代<고유명사 type="이름">淮王</고유명사>。終遂仙遊<line/>
之樂。周時柱史。何妨吏隱之名。苟保天成。奚言日損。<line/>
<페이지 number="ITKC_MO_0001A_A001_090D"/>景仰於其中有象。願知於此外無求。臣無任投辭懇<line/>
迫虔禱兢越之至。謹辭。</단락>
						</내용>
					</본문정보>
					<연계정보>
						<연계항목 type="이미지" 연계시작="ITKC_MO_0001A_A001_090C" 연계종료="ITKC_MO_0001A_A001_090D"/>
						<연계항목 type="번역문" 연계시작="ITKC_BT_0001A_0160_010_0100" 연계종료="ITKC_BT_0001A_0160_010_0100"/>
					</연계정보>
				</레벨4>
<레벨4 DCI="ITKC_MO_0001A_0160_010_0110_2003_A001_XML" id="ITKC_MO_0001A_0160_010_0110" type="최종정보" 자료생성일="2003-09-04">
					<메타정보>
						<제목정보>
							<제목>黃籙齋詞</제목>
						</제목정보>
						<저자정보 type="필자">
							<저자>
								<한글성명>최치원</한글성명>
								<한자성명>崔致遠</한자성명>
							</저자>
						</저자정보>
						<간행정보>
							<집수번호>a001</집수번호>
						</간행정보>
						<분류정보>
							<분류항목 type="문체분류">
								<분류내용 type="대분류">哀祭類</분류내용>
								<분류내용 type="중분류">其他類</분류내용>
							</분류항목>
						</분류정보>
					</메타정보>
					<본문정보>
						<내용>
<단락 align="left" indent="0">啓請如科儀。臣身拘俗網。志仰眞筌。雖窈窈冥冥至<line/>
道則無形可扣。而勤勤懇懇精心則有感必通。是以。<line/>
每勵焚修。敢安晷刻所。冀學海而終歸巨海。好龍而<line/>
不懼眞龍。豈貪輕擧之名。但效勤行之旨。然以早分<line/>
相印。久握兵符。當扶危靜亂之秋。有戮暴誅奸之役。<line/>
伏慮政條失所。刑律乖宜。愆違暗積於玄司。殃咎難<line/>
逃於黑籍。今則景銷木德。節啓火威。稽首昊天。叩心<line/>
<페이지 number="ITKC_MO_0001A_A001_091A"/>靈地。跼蹐而謹陳薄奠。禱祠而仰獻微誠。伏乞太上<line/>
三尊。十方衆聖。俯矜丹悃。深降洪慈。使電滅千災。雲<line/>
興百福。永資玄蔭。漸茂靈根。掃閫外之煙塵。早成勳<line/>
業。玩壺中之日月。免役夢思。臣無任悔過祈恩懇迫<line/>
惶恐之至。謹辭。</단락>
						</내용>
					</본문정보>
					<연계정보>
						<연계항목 type="이미지" 연계시작="ITKC_MO_0001A_A001_090D" 연계종료="ITKC_MO_0001A_A001_091A"/>
						<연계항목 type="번역문" 연계시작="ITKC_BT_0001A_0160_010_0110" 연계종료="ITKC_BT_0001A_0160_010_0110"/>
					</연계정보>
				</레벨4>
<레벨4 DCI="ITKC_MO_0001A_0160_010_0120_2003_A001_XML" id="ITKC_MO_0001A_0160_010_0120" type="최종정보" 자료생성일="2003-09-04">
					<메타정보>
						<제목정보>
							<제목>禳火齋詞</제목>
						</제목정보>
						<저자정보 type="필자">
							<저자>
								<한글성명>최치원</한글성명>
								<한자성명>崔致遠</한자성명>
							</저자>
						</저자정보>
						<간행정보>
							<집수번호>a001</집수번호>
						</간행정보>
						<분류정보>
							<분류항목 type="문체분류">
								<분류내용 type="대분류">哀祭類</분류내용>
								<분류내용 type="중분류">其他類</분류내용>
							</분류항목>
						</분류정보>
					</메타정보>
					<본문정보>
						<내용>
<단락 align="left" indent="0">年月日。啓請如科儀。於<고유명사 type="건물">紫極宮</고유명사>內修建<고유명사 type="건물">洞淵妙齋</고유명사>。三<line/>
日四夜轉經行道。爲禳當府火災。祈恩投辭。上諧虛<line/>
無元始天尊。伏以波蕩四溟。塵昏九野。遂見綿區匝<line/>
宇。未能滅祲消氛。臣雖志悅道風。而身沾睿澤。早託<line/>
<페이지 number="ITKC_MO_0001A_A001_091B"/>山河之誓。久臨<고유명사 type="지명">淮海</고유명사>之封。每愼撫綏。不遑寧息。粗安<line/>
一境。已涉五年。齋誠仰貢於上玄。妖氣願銷於下界。<line/>
豈料天心悔禍。必俟時期。地分罹殃。難逃曆數。方當<line/>
暮月。始起融風。遽興鄭國之災。難施爟斝。將救成都<line/>
之急。誰噀酒杯。所焮旣多。俱焚是慮。衆力猶勤於撤<line/>
屋。群心免駭於燎原。今則每念傷人。唯知罪己。仰投<line/>
靈宇。敬醮寶壇。祓禳夐異於四郊。寧拘古禮。祈禱遠<line/>
瞻於三島。但獻精誠。伏乞太上三尊。十方衆聖。曲流<line/>
玄澤。大挫陽精。使回祿知非。<고유명사 type="이름">祝融</고유명사>請罪。閭閻撲地。皆<line/>
除火宅之災。道路生風。永作水鄕之福。烝黎樂業。師<line/>
<페이지 number="ITKC_MO_0001A_A001_091C"/>旅懷安。構陰謀者自就消亡。歸善化者各資榮泰。齊<line/>
登壽域。仰望仙鄕。臣無任歸罪乞恩虔禱懇迫惶恐<line/>
之至。謹辭。</단락>
						</내용>
					</본문정보>
					<연계정보>
						<연계항목 type="이미지" 연계시작="ITKC_MO_0001A_A001_091A" 연계종료="ITKC_MO_0001A_A001_091C"/>
						<연계항목 type="번역문" 연계시작="ITKC_BT_0001A_0160_010_0120" 연계종료="ITKC_BT_0001A_0160_010_0120"/>
					</연계정보>
				</레벨4>
<레벨4 DCI="ITKC_MO_0001A_0160_010_0130_2003_A001_XML" id="ITKC_MO_0001A_0160_010_0130" type="최종정보" 자료생성일="2003-09-04">
					<메타정보>
						<제목정보>
							<제목><고유명사 type="건물">天王院</고유명사>齋詞</제목>
						</제목정보>
						<저자정보 type="필자">
							<저자>
								<한글성명>최치원</한글성명>
								<한자성명>崔致遠</한자성명>
							</저자>
						</저자정보>
						<간행정보>
							<집수번호>a001</집수번호>
						</간행정보>
						<분류정보>
							<분류항목 type="문체분류">
								<분류내용 type="대분류">哀祭類</분류내용>
								<분류내용 type="중분류">其他類</분류내용>
							</분류항목>
						</분류정보>
					</메타정보>
					<본문정보>
						<내용>
<단락 align="left" indent="0">唐中和二年太歲壬寅正月望日。具銜某敬請僧某<line/>
乙設齋于<고유명사 type="건물">法雲寺</고유명사><고유명사 type="건물">天王院</고유명사>。謹白言舍利佛大慈大悲<line/>
觀音菩薩。伏以欲界將傾。魔軍競起。九野塵昏於劫<line/>
燼。四溟波蕩於狂飆。諸侯志慕於宋公。星無三徙。聖<line/>
主德齊於漢帝。日未再中。不知天養鴟梟。地容螟蟘。<line/>
力鬪之群兇得便。義征之衆旅摧威。某也手握兵符。<line/>
<페이지 number="ITKC_MO_0001A_A001_091D"/>心抱將略。欲展焚枯之力。願成拯溺之功。是以。景仰<line/>
三歸。勤行十善。深憑護念。敢啓邀迎。宇內瘡痍。略假<line/>
醫王之術。世間疲瘵。遍希慈父之恩。今則幸遇初元。<line/>
精修美供。春露洒琉璃之境。曉風吹薝蔔之香。想其<line/>
舍衛城中。長老盡携弟子。<고유명사 type="건물">水精宮</고유명사>裏。天王便作主人。<line/>
伏願舍利佛大慈大悲觀世音菩薩。敎旣東流。跡能<line/>
西降。遠救閻浮之地。暫離兜率之天。問疾語言。不競<line/>
維摩之說。稱名功德。可逃羅刹之災。唯願共泛慈航。<line/>
齊揮智劍。寢驚濤於苦海。掃妖氣於昏衢。則乃慧燈<line/>
照天帝之心。法鼓破波臣之膽。靜銷諸惡。暫開方便<line/>
<페이지 number="ITKC_MO_0001A_A001_092A"/>之門。廣庇衆生。無惜慈悲之室。謹疏。</단락>
						</내용>
					</본문정보>
					<연계정보>
						<연계항목 type="이미지" 연계시작="ITKC_MO_0001A_A001_091C" 연계종료="ITKC_MO_0001A_A001_092A"/>
						<연계항목 type="번역문" 연계시작="ITKC_BT_0001A_0160_010_0130" 연계종료="ITKC_BT_0001A_0160_010_0130"/>
					</연계정보>
				</레벨4>
<레벨4 DCI="ITKC_MO_0001A_0160_010_0140_2003_A001_XML" id="ITKC_MO_0001A_0160_010_0140" type="최종정보" 자료생성일="2003-09-04">
					<메타정보>
						<제목정보>
							<제목>爲故昭義<고유명사 type="관직">僕射</고유명사>齋詞</제목>
						</제목정보>
						<저자정보 type="필자">
							<저자>
								<한글성명>최치원</한글성명>
								<한자성명>崔致遠</한자성명>
							</저자>
						</저자정보>
						<간행정보>
							<집수번호>a001</집수번호>
						</간행정보>
						<분류정보>
							<분류항목 type="문체분류">
								<분류내용 type="대분류">哀祭類</분류내용>
								<분류내용 type="중분류">其他類</분류내용>
							</분류항목>
						</분류정보>
					</메타정보>
					<본문정보>
						<내용>
<단락 align="left" indent="0">中和二年七月二十三日。爲故昭義姪孫<고유명사 type="관직">僕射</고유명사>及二<line/>
孫子敬。設齋于<고유명사 type="건물">法雲寺</고유명사>。聊憑法疏。用寫悲詞。以昭義<line/>
姪孫幼蘊壯圖。長居重任。不掃一室。有志四方。手運<line/>
豹韜。旣是吾家之事。身持龍節。累沾聖代之恩。至於<line/>
越海征蠻。對河分陝。立戰功於遐徼。傳理化於近藩。<line/>
愼守詔條。能諧物議。遂移上黨。實委外權。尋屬戎馬<line/>
生郊。陣虵出穴。遽令寇孼。直犯京華。頻興伐叛之師。<line/>
稍急訓戎之令。上將則雖期徇難。欲竭忠誠。小人則<line/>
<페이지 number="ITKC_MO_0001A_A001_092B"/>多是幸災。潛興狡計。叛徒忽至。橫禍斯侵。弘演納肝。<line/>
其誰能繼。酆舒傷目。所不忍言。噫。道則日彰。志惟天<line/>
奪。征旌永卷。飛旐遠來。言念彫零。莫勝悲慟。但以推<line/>
尋佛理。抑割俗情。旣知前世因緣。粗解此時冤痛。況<line/>
乃父立忠節。子揚孝名。古賢所稱。今我何恨。俾資冥<line/>
福。敬設妙齋。所願慧炬照迷。慈航援溺。早推誠於貫<line/>
日。終致樂於生天。子子孫孫。永絶怨讎之本。生生世<line/>
世。常逢安泰之期。謹疏。</단락>
						</내용>
					</본문정보>
					<연계정보>
						<연계항목 type="이미지" 연계시작="ITKC_MO_0001A_A001_092A" 연계종료="ITKC_MO_0001A_A001_092B"/>
						<연계항목 type="번역문" 연계시작="ITKC_BT_0001A_0160_010_0140" 연계종료="ITKC_BT_0001A_0160_010_0140"/>
					</연계정보>
				</레벨4>
<레벨4 DCI="ITKC_MO_0001A_0160_010_0150_2003_A001_XML" id="ITKC_MO_0001A_0160_010_0150" type="최종정보" 자료생성일="2003-09-04">
					<메타정보>
						<제목정보>
							<제목>爲故昭義<고유명사 type="관직">僕射</고유명사>齋詞</제목>
						</제목정보>
						<저자정보 type="필자">
							<저자>
								<한글성명>최치원</한글성명>
								<한자성명>崔致遠</한자성명>
							</저자>
						</저자정보>
						<간행정보>
							<집수번호>a001</집수번호>
						</간행정보>
						<분류정보>
							<분류항목 type="문체분류">
								<분류내용 type="대분류">哀祭類</분류내용>
								<분류내용 type="중분류">其他類</분류내용>
							</분류항목>
						</분류정보>
					</메타정보>
					<본문정보>
						<내용>
<단락 align="left" indent="0">中和二年七月二十七日。某官某乙奉<고유명사 type="관직">太尉</고유명사>處分。爲<line/>
<페이지 number="ITKC_MO_0001A_A001_092C"/>故昭義<고유명사 type="관직">僕射</고유명사>。於<고유명사 type="건물">法雲寺</고유명사>設三百僧齋。並寫<고유명사 type="서명">金光明經</고유명사><line/>
五部。<고유명사 type="서명">法華經</고유명사>一部。永充供養。蓋聆佛修慧力。普濟群<line/>
迷。人發信心。終成善願。苟得影從至敎。必能響答虔<line/>
誠。伏以昭義<고유명사 type="관직">僕射</고유명사>夙振雄圖。繼分重寄。將軍投袂。練<line/>
兵而方切專征。天子翦衣。飛詔而唯憑妙略。佇建彀<line/>
中之勳業。忽罹意外之災殃。不弔昊天奪我良胤。今<line/>
則敬投蓮宇。虔設桑門。仍 <원주>缺</원주> 貝葉之眞蹤。仰奉<고유명사 type="서명">法華</고유명사><line/>
之妙義。伏願乘玆功德。解彼冤讎。災星昔照於<고유명사 type="지명">預州</고유명사>。<line/>
已推定分。慧日分懸於覺路。永絶良緣。謹疏。</단락>
						</내용>
					</본문정보>
					<연계정보>
						<연계항목 type="이미지" 연계시작="ITKC_MO_0001A_A001_092B" 연계종료="ITKC_MO_0001A_A001_092C"/>
						<연계항목 type="번역문" 연계시작="ITKC_BT_0001A_0160_010_0150" 연계종료="ITKC_BT_0001A_0160_010_0150"/>
					</연계정보>
				</레벨4></레벨3></레벨2></레벨1></아이템>